DeepSeekfree/__init__.py
DeepSeekfree/deepseek.py
DeepSeekfree/errors.py
DeepSeekfree/pow.py
test/test.py
DeepSeekfree-0.7.0.dist-info/LICENSE
DeepSeekfree-0.7.0.dist-info/METADATA
DeepSeekfree-0.7.0.dist-info/WHEEL
DeepSeekfree-0.7.0.dist-info/top_level.txt
DeepSeekfree-0.7.0.dist-info/RECORD
