Metadata-Version: 2.2
Name: DeepSeekfree
Version: 0.7.0
Summary: A small example package
Author-email: danel-phang <danel_phang@outlook.com>
Project-URL: Homepage, https://github.com/danel_phang/DeepSeekfree
Project-URL: Issues, https://github.com/danel_phang/DeepSeekfree/issues
Classifier: Programming Language :: Python :: 3
Classifier: License :: OSI Approved :: GNU Affero General Public License v3
Classifier: Operating System :: OS Independent
Requires-Python: >=3.7
License-File: LICENSE
